{"cameraMode":{"drawMode":0,"name":"Shaded","section":"Shading Mode"},"sceneLighting":true,"audioPlay":false,"sceneViewState":{"showFog":true,"showMaterialUpdate":false,"showSkybox":true,"showFlares":true,"showImageEffects":true,"showParticleSystems":true},"in2DMode":false,"pivot":{"x":352.3231506347656,"y":200.54263305664063,"z":395.46893310546877},"rotation":{"x":-0.05636490508913994,"y":0.01107549387961626,"z":-0.0006251657614484429,"w":-0.9983537197113037},"size":998.80859375,"orthographic":false}